myCalculatorPackageP/__init__.py
myCalculatorPackageP/division/__init__.py
myCalculatorPackageP/division/divide.py
myCalculatorPackageP/multiplication/__init__.py
myCalculatorPackageP/multiplication/multiply.py
myCalculatorPackageP-0.0.2.dist-info/LICENSE.txt
myCalculatorPackageP-0.0.2.dist-info/METADATA
myCalculatorPackageP-0.0.2.dist-info/WHEEL
myCalculatorPackageP-0.0.2.dist-info/top_level.txt
myCalculatorPackageP-0.0.2.dist-info/RECORD
